artmeta/__init__.py
artmeta/__main__.py
artmeta/cli.py
artmeta/core.py
artmeta/utils.py
artmeta/validators.py
artmeta/generators/__init__.py
artmeta/generators/ams.py
artmeta/generators/base.py
artmeta/generators/elsevier.py
artmeta/generators/hal.py
artmeta/generators/siam.py
artmeta/generators/springer.py
artmeta/generators/standard.py
artmeta/templates/amsart.tex.j2
artmeta/templates/article.tex.j2
artmeta/templates/elsarticle.tex.j2
artmeta/templates/hal.xml.j2
artmeta/templates/siamart.tex.j2
artmeta/templates/svjour3.tex.j2
artmeta-0.2.5.dist-info/licenses/LICENSE
artmeta-0.2.5.dist-info/METADATA
artmeta-0.2.5.dist-info/WHEEL
artmeta-0.2.5.dist-info/entry_points.txt
artmeta-0.2.5.dist-info/top_level.txt
artmeta-0.2.5.dist-info/RECORD
