Metadata-Version: 2.4
Name: artmeta
Version: 0.2.5
Summary: Gestionnaire de métadonnées pour articles académiques - génération LaTeX et exports HAL/ArXiv
Author-email: Nicolas Klutchnikoff <nicolas.klutchnikoff@univ-rennes2.fr>
License-Expression: MIT
Project-URL: Homepage, https://plmlab.math.cnrs.fr/nicolas.klutchnikoff/artmeta
Project-URL: Documentation, https://artmeta.readthedocs.io
Project-URL: Repository, https://plmlab.math.cnrs.fr/nicolas.klutchnikoff/artmeta
Project-URL: Issues, https://plmlab.math.cnrs.fr/nicolas.klutchnikoff/artmeta/-/issues
Keywords: latex,academic,metadata,hal,arxiv,publishing
Classifier: Development Status :: 3 - Alpha
Classifier: Intended Audience :: Science/Research
Classifier: Topic :: Text Processing :: Markup :: LaTeX
Classifier: Programming Language :: Python :: 3
Classifier: Programming Language :: Python :: 3.8
Classifier: Programming Language :: Python :: 3.9
Classifier: Programming Language :: Python :: 3.10
Classifier: Programming Language :: Python :: 3.11
Classifier: Programming Language :: Python :: 3.12
Requires-Python: >=3.8
License-File: LICENSE
Requires-Dist: pyyaml>=6.0
Requires-Dist: jinja2>=3.1
Provides-Extra: dev
Requires-Dist: pytest>=7.0; extra == "dev"
Requires-Dist: pytest-cov>=4.0; extra == "dev"
Requires-Dist: black>=23.0; extra == "dev"
Requires-Dist: ruff>=0.1.0; extra == "dev"
Provides-Extra: docs
Requires-Dist: mkdocs>=1.5.0; extra == "docs"
Requires-Dist: mkdocs-material>=9.0.0; extra == "docs"
Dynamic: license-file
